GearAPI/__init__.py
GearAPI/client.py
GearAPI/exceptions.py
GearAPI/rest_adaptor.py
GearAPI/helpers/__init__.py
GearAPI/helpers/helpers.py
GearAPI/models/__init__.py
GearAPI/models/rest_adaptor_models.py
GearAPI/resource/__init__.py
GearAPI/resource/alarms_resource.py
GearAPI/resource/events_resource.py
GearAPI/resource/inventory_resource.py
GearAPI/resource/measurements_resource.py
GearAPI/resource/realtime_notification.py
GearAPI/utilis/__init__.py
GearAPI/utilis/utilis.py
gearapi-0.15.11.dist-info/METADATA
gearapi-0.15.11.dist-info/WHEEL
gearapi-0.15.11.dist-info/top_level.txt
gearapi-0.15.11.dist-info/RECORD
