Metadata-Version: 2.4
Name: GearAPI
Version: 0.15.11
Summary: An API wrapper for cumulocity API. Made for researcher. Focus on Measurements and events resources from GEAR data
Home-page: https://github.com/kajimadev-KaTRIS/GearAPI
Author: Darius Lim Hong Yi
Author-email: hy.lim@kajima.com.sg
Classifier: Programming Language :: Python :: 3
Classifier: License :: OSI Approved :: MIT License
Classifier: Operating System :: OS Independent
Requires-Python: >=3.6
Requires-Dist: pandas<=2.2.2
Requires-Dist: requests
Requires-Dist: dataclasses==0.6
Requires-Dist: wheel==0.37.1
Requires-Dist: websocket-client==1.8.0
Dynamic: author
Dynamic: author-email
Dynamic: classifier
Dynamic: description
Dynamic: description-content-type
Dynamic: home-page
Dynamic: requires-dist
Dynamic: requires-python
Dynamic: summary
